generic_api_wrapper/__init__.py
generic_api_wrapper/aws_iam_auth.py
generic_api_wrapper/generic_api_wrapper.py
generic_api_wrapper-0.2.0.dist-info/LICENSE
generic_api_wrapper-0.2.0.dist-info/METADATA
generic_api_wrapper-0.2.0.dist-info/WHEEL
generic_api_wrapper-0.2.0.dist-info/top_level.txt
generic_api_wrapper-0.2.0.dist-info/RECORD
