Metadata-Version: 2.1
Name: generic-api-wrapper
Version: 0.2.0
Summary: Generic API wrapper
Home-page: https://github.com/grishasergii/generic-api-wrapper
Author: Sergii Gryshkevych
Author-email: 
License: MIT license
Keywords: api,wrapper,generic,rest api
Platform: UNKNOWN
Classifier: Development Status :: 2 - Pre-Alpha
Classifier: Intended Audience :: Developers
Classifier: License :: OSI Approved :: MIT License
Classifier: Natural Language :: English
Classifier: Programming Language :: Python :: 3
Classifier: Programming Language :: Python :: 3.6
Classifier: Programming Language :: Python :: 3.7
Classifier: Programming Language :: Python :: 3.8
Classifier: Programming Language :: Python :: 3.9
Requires-Python: >=3.6
License-File: LICENSE
Requires-Dist: requests
Requires-Dist: urllib3
Requires-Dist: boto3
Requires-Dist: aws-requests-auth
